etch/admin_password_updater.py
etch/app.py
etch/auth.py
etch/cli.py
etch/markdown_extensions.py
etch/utils.py
etch-0.1.0.dist-info/licenses/LICENSE
etch-0.1.0.dist-info/METADATA
etch-0.1.0.dist-info/WHEEL
etch-0.1.0.dist-info/entry_points.txt
etch-0.1.0.dist-info/top_level.txt
etch-0.1.0.dist-info/RECORD
