Metadata-Version: 2.4
Name: etch
Version: 0.1.0
Summary: A featherlight Markdown + python personal site framework inspired by pain, built by Claude
Author-email: Rob Kimball <rob@rgk.io>
License: Apache 2.0
Project-URL: Homepage, https://rgk.io/projects/etch
Project-URL: Repository, https://github.com/rgkimball/etch
Project-URL: Issues, https://github.com/rgkimball/etch/issues
Keywords: markdown,flask,web framework,minimal,static
Classifier: Development Status :: 3 - Alpha
Classifier: Environment :: Web Environment
Classifier: Framework :: Flask
Classifier: License :: OSI Approved :: Apache Software License
Classifier: Programming Language :: Python :: 3
Classifier: Programming Language :: Python :: 3.9
Classifier: Topic :: Internet :: WWW/HTTP :: Site Management
Classifier: Topic :: Software Development :: Libraries :: Application Frameworks
Requires-Python: >=3.9
License-File: LICENSE
Dynamic: license-file
